{
  "epoch": 0,
  "neurons": [
    {
      "x": 0.0,
      "y": 0.0,
      "value": 0.2345064437390419,
      "layer": 0
    },
    {
      "x": 0.0,
      "y": 0.0,
      "value": 0.0,
      "layer": 0
    },
    {
      "x": 0.0,
      "y": 0.0,
      "value": 0.3484064563977424,
      "layer": 0
    },
    {
      "x": 0.0,
      "y": 0.0,
      "value": 0.0,
      "layer": 0
    },
    {
      "x": 0.0,
      "y": 0.0,
      "value": 0.0,
      "layer": 0
    },
    {
      "x": 0.0,
      "y": 0.0,
      "value": 0.0,
      "layer": 0
    },
    {
      "x": 0.0,
      "y": 0.0,
      "value": 0.0,
      "layer": 0
    },
    {
      "x": 0.0,
      "y": 0.0,
      "value": 0.0,
      "layer": 0
    },
    {
      "x": 0.0,
      "y": 0.0,
      "value": 0.0,
      "layer": 0
    },
    {
      "x": 0.0,
      "y": 0.0,
      "value": 0.0,
      "layer": 0
    },
    {
      "x": 0.0,
      "y": 0.0,
      "value": 0.0,
      "layer": 0
    },
    {
      "x": 0.0,
      "y": 0.0,
      "value": 0.0,
      "layer": 0
    },
    {
      "x": 0.0,
      "y": 0.0,
      "value": 0.0,
      "layer": 0
    },
    {
      "x": 0.0,
      "y": 0.0,
      "value": 0.0,
      "layer": 0
    },
    {
      "x": 0.0,
      "y": 0.0,
      "value": 0.0,
      "layer": 0
    },
    {
      "x": 1.5789093875910911,
      "y": 0.3348373565277205,
      "value": 0.0004016750819175225,
      "layer": -1
    },
    {
      "x": -3.503118650285985,
      "y": 0.672354768631239,
      "value": -0.0005564087739015182,
      "layer": -1
    },
    {
      "x": 1.0130454711363948,
      "y": -3.8708429810556377,
      "value": -0.00034283218881648724,
      "layer": -1
    },
    {
      "x": -4.033941668156473,
      "y": -3.3363625420675245,
      "value": 0,
      "layer": -1
    },
    {
      "x": 4.4769392422349075,
      "y": -0.6676849744851419,
      "value": 0,
      "layer": -1
    },
    {
      "x": -2.545181238592449,
      "y": -2.2529660803442297,
      "value": -7.062827018462622e-05,
      "layer": -1
    },
    {
      "x": -3.2153958927927473,
      "y": -3.8051749566922286,
      "value": -2.9966133059665998e-05,
      "layer": -1
    },
    {
      "x": -3.3506219342036783,
      "y": 1.4872483121622704,
      "value": 0.00018324311827731956,
      "layer": -1
    },
    {
      "x": 2.7751138937539928,
      "y": -0.19866609775652488,
      "value": -9.22357601880853e-05,
      "layer": -1
    },
    {
      "x": -0.6528945100556562,
      "y": -4.949914250906517,
      "value": 0,
      "layer": -1
    },
    {
      "x": -1.6834277736450454,
      "y": -1.8057676223946606,
      "value": -0.0011225294831233735,
      "layer": -1
    },
    {
      "x": -0.5194407399898395,
      "y": 0.828489673005941,
      "value": 0.005333092863764678,
      "layer": -1
    },
    {
      "x": 3.695455453974027,
      "y": 1.7335321674851292,
      "value": 0.00038505918932126547,
      "layer": -1
    },
    {
      "x": 0.25353848876590224,
      "y": 4.105338176465974,
      "value": 0,
      "layer": -1
    },
    {
      "x": 1.0210486873894933,
      "y": -4.37226376188479,
      "value": 0,
      "layer": -1
    },
    {
      "x": -0.38558737203565663,
      "y": -0.9887011993109764,
      "value": -0.003181104483659947,
      "layer": -1
    },
    {
      "x": 0.849350493343958,
      "y": 0.38667048423143147,
      "value": 0.004004365365858249,
      "layer": -1
    },
    {
      "x": -3.3420355946779234,
      "y": -0.5865318254641245,
      "value": -0.0005802533204436672,
      "layer": -1
    },
    {
      "x": -0.8482630678216729,
      "y": -4.646821702121688,
      "value": 0,
      "layer": -1
    },
    {
      "x": 0.35418451316212884,
      "y": -4.494270581779036,
      "value": 0,
      "layer": -1
    },
    {
      "x": -3.912435873730309,
      "y": -0.4592166965118025,
      "value": -0.0001452266675891129,
      "layer": -1
    },
    {
      "x": -0.14944649194928683,
      "y": -0.41359716191615625,
      "value": -0.002466812666143809,
      "layer": -1
    },
    {
      "x": 0.011121848422556369,
      "y": -0.5291253072597577,
      "value": 0.010055357727429777,
      "layer": -1
    },
    {
      "x": 3.979415356273188,
      "y": 1.9787034733776725,
      "value": 0.0002637080037379576,
      "layer": -1
    },
    {
      "x": 1.4952911823737534,
      "y": 4.095405975236686,
      "value": 0,
      "layer": -1
    }
  ]
}